[
  {
    "id": "post-1",
    "position": 1,
    "url": "https://www.facebook.com/photo/?fbid=10232533295375249&set=a.1655316943159",
    "title": "GRACIAS SE칌OR!",
    "description": "por tu fidelidad游봋",
    "zoom": 1.3,
    "offsetX": 0,
    "offsetY": -10
  },
  {
    "id": "post-1",
    "position": -1,
    "url": "https://www.facebook.com/TU_PAGINA/posts/123456789",
    "title": "Otra publicaci칩n",
    "description": "Otra descripci칩n"
  },
  {
    "id": "post-3",
    "position": -1,
    "url": "https://www.facebook.com/photo/?fbid=ejemplo",
    "title": "Esta publicaci칩n est치 oculta",
    "description": "No aparecer치 porque position es -1"
  }
]
